README.rst
setup.py
initpy/__init__.py
initpy/compact.py
initpy/creator.py
initpy/exceptions.py
initpy/prompt.py
initpy/run.py
initpy.egg-info/PKG-INFO
initpy.egg-info/SOURCES.txt
initpy.egg-info/dependency_links.txt
initpy.egg-info/entry_points.txt
initpy.egg-info/top_level.txt
initpy/templates/__init__.py
initpy/templates/blank.py
initpy/templates/falcon.py
initpy/templates/flask.py
initpy/templates/tornado_web.py